deflakyzavr/__init__.py
deflakyzavr/__main__.py
deflakyzavr/_deflakyzavr_plugin.py
deflakyzavr/_jira_stdout.py
deflakyzavr/_messages.py
deflakyzavr/py.typed
deflakyzavr/version
deflakyzavr/version.py
deflakyzavr-0.1.0.data/scripts/deflakyzavr
deflakyzavr-0.1.0.dist-info/licenses/LICENSE
deflakyzavr-0.1.0.dist-info/METADATA
deflakyzavr-0.1.0.dist-info/WHEEL
deflakyzavr-0.1.0.dist-info/top_level.txt
deflakyzavr-0.1.0.dist-info/RECORD
