Metadata-Version: 2.4
Name: deflakyzavr
Version: 0.1.0
Summary: vedro.io plugin for creating ticket into jira for flaky duty
Home-page: https://github.com/Legion18z/deflakyzavr
Author: Andrey Maslov
Author-email: legionus18z@gmail.com
License: Apache-2.0
Classifier: License :: OSI Approved :: Apache Software License
Classifier: Programming Language :: Python :: 3.10
Classifier: Typing :: Typed
Requires-Python: >=3.7
License-File: LICENSE
Requires-Dist: jira<3.7,>=3.6.0
Requires-Dist: rtry<2.0,>=1.4.0
Dynamic: author
Dynamic: author-email
Dynamic: classifier
Dynamic: description
Dynamic: description-content-type
Dynamic: home-page
Dynamic: license
Dynamic: license-file
Dynamic: requires-dist
Dynamic: requires-python
Dynamic: summary
